{
  "markers": [
    {
      "name": "Nina Lucia Fire",
      "type": "Wildfire",
      "summary": " The Nina Lucia Fire started along County Road 273 approximately 6...",
      "state": "TEXAS",
      "updated": "2022-04-20 09:39:51",
      "lat": "32.175",
      "lng": "-100.567",
      "size": "564 Acres",
      "url": "/incident/8065/",
      "id": "8065",
      "contained": "95"
    },
    {
      "name": "Nogal Canyon Fire",
      "type": "Wildfire",
      "summary": "The Nogal Canyon Fire that started on April 12, 2022, has burned 6...",
      "state": "NEW MEXICO",
      "updated": "2022-04-20 09:37:36",
      "lat": "33.511",
      "lng": "-105.747",
      "size": "412 Acres",
      "url": "/incident/8062/",
      "id": "8062",
      "contained": "70"
    },
    {
      "name": "McBride Fire",
      "type": "Wildfire",
      "summary": "The McBride Fire started on April 12, 2022 around 2:30 pm on Warrior...",
      "state": "NEW MEXICO",
      "updated": "2022-04-20 09:36:33",
      "lat": "33.333",
      "lng": "-105.635",
      "size": "6,159 Acres",
      "url": "/incident/8061/",
      "id": "8061",
      "contained": "84"
    },
    {
      "name": "Hermits Peak Fire",
      "type": "Wildfire",
      "summary": " The Las Dispensas prescribed fire on the Pecos/Las Vegas Ranger...",
      "state": "NEW MEXICO",
      "updated": "2022-04-20 09:13:21",
      "lat": "35.718",
      "lng": "-105.399",
      "size": "7,581 Acres",
      "url": "/incident/8049/",
      "id": "8049",
      "contained": "81"
    },
    {
      "name": "Tunnel Fire",
      "type": "Wildfire",
      "summary": "The Tunnel Fire, located approximately 14 miles northeast of...",
      "state": "ARIZONA",
      "updated": "2022-04-20 09:04:35",
      "lat": "35.304",
      "lng": "-111.589",
      "size": "16,625 Acres",
      "url": "/incident/8068/",
      "id": "8068",
      "contained": "0"
    },
    {
      "name": "Crooks Fire",
      "type": "Wildfire",
      "summary": "Ryan Barela’s Arizona Central West Zone Type 3 Incident Management...",
      "state": "ARIZONA",
      "updated": "2022-04-20 08:57:23",
      "lat": "34.403",
      "lng": "-112.426",
      "size": "1,600 Acres",
      "url": "/incident/8067/",
      "id": "8067",
      "contained": "0"
    },
    {
      "name": "Cooks Peak",
      "type": "Wildfire",
      "summary": "The Cooks Peak Fire is located on private land north of Ocate in Mora...",
      "state": "NEW MEXICO",
      "updated": "2022-04-19 23:16:24",
      "lat": "36.243",
      "lng": "-105.038",
      "size": "3,500 Acres",
      "url": "/incident/8066/",
      "id": "8066",
      "contained": "0"
    },
    {
      "name": "Calf Canyon",
      "type": "Wildfire",
      "summary": "The Calf Canyon Fire is located on the Santa Fe National Forest in...",
      "state": "NEW MEXICO",
      "updated": "2022-04-19 22:45:20",
      "lat": "35.759",
      "lng": "-105.503",
      "size": "300 Acres",
      "url": "/incident/8069/",
      "id": "8069",
      "contained": "0"
    },
    {
      "name": "Big Hole Fire",
      "type": "Wildfire",
      "summary": "",
      "state": "NEW MEXICO",
      "updated": "2022-04-19 12:54:00",
      "lat": "34.665",
      "lng": "-106.747",
      "size": "890 Acres",
      "url": "/incident/8059/",
      "id": "8059",
      "contained": "85"
    },
    {
      "name": "Tiger Fire",
      "type": "Wildfire",
      "summary": "This will be the final news release unless there are significant...",
      "state": "ARIZONA",
      "updated": "2022-04-18 19:51:36",
      "lat": "34.139",
      "lng": "-112.218",
      "size": "16,278 Acres",
      "url": "/incident/7595/",
      "id": "7595",
      "contained": "100"
    },
    {
      "name": "GWJ National Forest Prescribed Burns",
      "type": "Prescribed Fire",
      "summary": "The George Washington and Jefferson National Forests will conduct...",
      "state": "VIRGINIA",
      "updated": "2022-04-15 06:26:48",
      "lat": "37.671",
      "lng": "-79.861",
      "size": "0 Acres",
      "url": "/incident/7945/",
      "id": "7945",
      "contained": "0"
    },
    {
      "name": "Side Oats",
      "type": "Wildfire",
      "summary": "The Side Oats fire started on April 13, 2022 at approximately 2:15 pm...",
      "state": "TEXAS",
      "updated": "2022-04-13 20:56:50",
      "lat": "33.133",
      "lng": "-101.903",
      "size": "1,477 Acres",
      "url": "/incident/8063/",
      "id": "8063",
      "contained": "100"
    },
    {
      "name": "Animas City Mountain Prescribed Burn",
      "type": "Prescribed Fire",
      "summary": " In order to reduce the risk of high-intensity wildfire, improve...",
      "state": "COLORADO",
      "updated": "2022-04-13 18:55:21",
      "lat": "37.323",
      "lng": "-107.872",
      "size": "0 Acres",
      "url": "/incident/7688/",
      "id": "7688",
      "contained": "0"
    },
    {
      "name": "Research Fire",
      "type": "Wildfire",
      "summary": "Research Fire started on April 12, 2022 at approximately 2:00...",
      "state": "TEXAS",
      "updated": "2022-04-13 13:32:44",
      "lat": "33.64",
      "lng": "-101.997",
      "size": "61 Acres",
      "url": "/incident/8060/",
      "id": "8060",
      "contained": "100"
    },
    {
      "name": "Overflow Fire",
      "type": "Wildfire",
      "summary": "On April 7, 2022, the Bureau of Land Management (BLM) declared the...",
      "state": "NEW MEXICO",
      "updated": "2022-04-13 11:15:59",
      "lat": "33.269",
      "lng": "-104.363",
      "size": "1,900 Acres",
      "url": "/incident/8053/",
      "id": "8053",
      "contained": "100"
    },
    {
      "name": "Burke Fire",
      "type": "Wildfire",
      "summary": " On Monday, April 11th, Texas A&amp;M Forest Service was requested to...",
      "state": "TEXAS",
      "updated": "2022-04-12 14:30:22",
      "lat": "31.404",
      "lng": "-95.527",
      "size": "400 Acres",
      "url": "/incident/8058/",
      "id": "8058",
      "contained": "100"
    },
    {
      "name": "Southwest District BLM Prescribed Fire ",
      "type": "Prescribed Fire",
      "summary": "The Bureau of Land Management Southwest District plans to conduct...",
      "state": "COLORADO",
      "updated": "2022-04-12 11:26:51",
      "lat": "37.903",
      "lng": "-108.826",
      "size": "0 Acres",
      "url": "/incident/7852/",
      "id": "7852",
      "contained": "0"
    },
    {
      "name": "Bitterroot Spring RX Fire 2022",
      "type": "Prescribed Fire",
      "summary": "See the 'Announcements' and 'News' Tabs for the latest information on...",
      "state": "MONTANA",
      "updated": "2022-04-09 19:00:36",
      "lat": "46.081",
      "lng": "-114.176",
      "size": "0 Acres",
      "url": "/incident/8024/",
      "id": "8024",
      "contained": "0"
    },
    {
      "name": "Daniel's Ranch RX",
      "type": "Prescribed Fire",
      "summary": "On April 6th and 7th, Big Bend National Park staff plan to initiate a...",
      "state": "TEXAS",
      "updated": "2022-04-06 13:06:38",
      "lat": "29.18",
      "lng": "-102.961",
      "size": "33 Acres",
      "url": "/incident/8048/",
      "id": "8048",
      "contained": "0"
    },
    {
      "name": "Presumido Peak Fire",
      "type": "Wildfire",
      "summary": "This fire is 100% contained at 2,591 acres. All resources have been...",
      "state": "ARIZONA",
      "updated": "2022-04-05 11:48:47",
      "lat": "31.567",
      "lng": "-111.621",
      "size": "2,591 Acres",
      "url": "/incident/8036/",
      "id": "8036",
      "contained": "100"
    },
    {
      "name": "Kaibab NF South Zone Rx Fire",
      "type": "Prescribed Fire",
      "summary": "The Spring 2022 prescribed fire season is upon us. Fire managers will...",
      "state": "ARIZONA",
      "updated": "2022-04-01 17:18:52",
      "lat": "35.186",
      "lng": "-112.217",
      "size": "0 Acres",
      "url": "/incident/5922/",
      "id": "5922",
      "contained": "0"
    },
    {
      "name": "San Juan NF Prescribed Fire Program",
      "type": "Prescribed Fire",
      "summary": "The San Juan National Forest Fuels Management Staff are planning pile...",
      "state": "COLORADO",
      "updated": "2022-03-29 10:46:18",
      "lat": "37.279",
      "lng": "-107.882",
      "size": "0 Acres",
      "url": "/incident/6288/",
      "id": "6288",
      "contained": "0"
    },
    {
      "name": "Jim Post-Fire BAER",
      "type": "Burned Area Emergency Response",
      "summary": " THREE PHASES OF WILDFIRE RECOVERY  There are three phases of...",
      "state": "CALIFORNIA",
      "updated": "2022-03-28 18:51:09",
      "lat": "33.741",
      "lng": "-117.462",
      "size": "0 Acres",
      "url": "/incident/8000/",
      "id": "8000",
      "contained": "0"
    },
    {
      "name": "Cleveland RX Burning 2022",
      "type": "Prescribed Fire",
      "summary": "Each year the Cleveland National Forest conducts prescribed burns...",
      "state": "CALIFORNIA",
      "updated": "2022-03-28 17:24:27",
      "lat": "33.3",
      "lng": "-116.801",
      "size": "0 Acres",
      "url": "/incident/7317/",
      "id": "7317",
      "contained": "0"
    },
    {
      "name": "2022 Humboldt-Toiyabe Prescribed Fire",
      "type": "Prescribed Fire",
      "summary": " Planned Projects | Current Projects | Current PhotosAs part of...",
      "state": "NEVADA",
      "updated": "2022-03-21 12:53:39",
      "lat": "39.524",
      "lng": "-119.769",
      "size": "0 Acres",
      "url": "/incident/7310/",
      "id": "7310",
      "contained": "0"
    },
    {
      "name": "Indiana Dunes NP Spring 2022",
      "type": "Prescribed Fire",
      "summary": " Indiana Dunes National Park is planning 6 prescribed fires for the...",
      "state": "INDIANA",
      "updated": "2022-03-17 11:14:52",
      "lat": "41.617",
      "lng": "-87.19",
      "size": "0 Acres",
      "url": "/incident/8001/",
      "id": "8001",
      "contained": "0"
    },
    {
      "name": "Hoosier National Forest Prescribed Fire ",
      "type": "Prescribed Fire",
      "summary": "Bedford, Indiana. October 22, 2021 — The U.S. Forest Service plans...",
      "state": "INDIANA",
      "updated": "2022-03-16 08:50:44",
      "lat": "38.556",
      "lng": "-86.468",
      "size": "0 Acres",
      "url": "/incident/7887/",
      "id": "7887",
      "contained": "0"
    },
    {
      "name": "Caldor Post-Fire BAER",
      "type": "Burned Area Emergency Response",
      "summary": "SPECIAL SAFETY NOTE: Everyone near and downstream from the burned...",
      "state": "CALIFORNIA",
      "updated": "2022-02-02 15:24:27",
      "lat": "38.753",
      "lng": "-120.333",
      "size": "0 Acres",
      "url": "/incident/7842/",
      "id": "7842",
      "contained": "0"
    },
    {
      "name": "River Complex Post-Fire BAER",
      "type": "Burned Area Emergency Response",
      "summary": " SPECIAL SAFETY NOTE: Everyone near and downstream from the burned...",
      "state": "CALIFORNIA",
      "updated": "2022-02-01 12:55:24",
      "lat": "41.222",
      "lng": "-123.207",
      "size": "0 Acres",
      "url": "/incident/7868/",
      "id": "7868",
      "contained": "0"
    }
  ]
}
